rachiopy/__init__.py
rachiopy/device.py
rachiopy/flexschedulerule.py
rachiopy/notification.py
rachiopy/person.py
rachiopy/rachioobject.py
rachiopy/schedulerule.py
rachiopy/zone.py
RachioPy-1.0.3.dist-info/LICENSE.txt
RachioPy-1.0.3.dist-info/METADATA
RachioPy-1.0.3.dist-info/WHEEL
RachioPy-1.0.3.dist-info/top_level.txt
RachioPy-1.0.3.dist-info/RECORD
