Metadata-Version: 2.1
Name: RachioPy
Version: 1.0.3
Summary: A Python module for the Rachio API.
Home-page: https://github.com/rfverbruggen/rachiopy
Author: Robbert Verbruggen
Author-email: rfverbruggen@icloud.com
License: MIT
Download-URL: https://github.com/rfverbruggen/rachiopy/archive/1.0.3.tar.gz
Project-URL: Bug Reports, https://github.com/rfverbruggen/rachiopy/issues
Platform: Cross Platform
Classifier: Development Status :: 5 - Production/Stable
Classifier: Intended Audience :: Developers
Classifier: License :: OSI Approved :: MIT License
Classifier: Operating System :: OS Independent
Classifier: Programming Language :: Python :: 3
Classifier: Topic :: Software Development
Requires-Dist: requests
